latexplotlib/__init__.py
latexplotlib/_latexplotlib.py
latexplotlib-0.1.1.dist-info/LICENSE
latexplotlib-0.1.1.dist-info/METADATA
latexplotlib-0.1.1.dist-info/WHEEL
latexplotlib-0.1.1.dist-info/top_level.txt
latexplotlib-0.1.1.dist-info/RECORD
