Metadata-Version: 2.1
Name: latexplotlib
Version: 0.1.1
Summary: Perfect matplotlib figures for latex
Home-page: https://github.com/ConstantinGahr/latexplotlib
Author: Constantin Gahr
Author-email: constantin.gahr+latexplotlib@gmail.com
License: MIT
Project-URL: Bug Tracker, https://github.com/ConstantinGahr/latexplotlib/issues
Keywords: matplotlib-style-sheets,matplotlib-figures,latex,matplotlib-styles,python
Platform: UNKNOWN
Classifier: Programming Language :: Python :: 3
Classifier: License :: OSI Approved :: MIT License
Classifier: Operating System :: OS Independent
Requires-Python: >=3.6
License-File: LICENSE
Requires-Dist: appdirs
Requires-Dist: matplotlib
